metapackage.py
pyspine-0.0.14.dist-info/METADATA
pyspine-0.0.14.dist-info/WHEEL
pyspine-0.0.14.dist-info/licenses/LICENSE
pyspine-0.0.14.dist-info/RECORD
