Metadata-Version: 2.1
Name: pyspine
Version: 0.0.14
Summary: Spine: The backbone of your project
Project-URL: Homepage, https://github.com/shaharluftig/spine
Author-email: Shahar Luftig <shaharluftig@gmail.com>
License:                                  Apache License
License-File: LICENSE
Keywords: core,dag,data enginnering,data pipline,dataframe,spine,workflow
Classifier: Intended Audience :: Science/Research
Classifier: Operating System :: OS Independent
Classifier: Programming Language :: Python
Classifier: Programming Language :: Python :: 3
Classifier: Programming Language :: Python :: 3 :: Only
Classifier: Programming Language :: Python :: 3.7
Classifier: Programming Language :: Python :: 3.8
Classifier: Programming Language :: Python :: 3.9
Classifier: Programming Language :: Python :: 3.10
Classifier: Programming Language :: Python :: 3.11
Classifier: Topic :: Scientific/Engineering
Requires-Python: >=3.7
Requires-Dist: spinecore
Requires-Dist: spinelibs
Provides-Extra: all
Requires-Dist: spinecore[polars]; extra == 'all'
Requires-Dist: spinecore[spark]; extra == 'all'
Requires-Dist: spinelibs[polars]; extra == 'all'
Requires-Dist: spinelibs[spark]; extra == 'all'
Provides-Extra: dev
Requires-Dist: pytest-asyncio~=0.20.3; extra == 'dev'
Requires-Dist: pytest~=7.2.2; extra == 'dev'
Requires-Dist: spinecore[all]; extra == 'dev'
Requires-Dist: spinelibs[all]; extra == 'dev'
Provides-Extra: polars
Requires-Dist: spinecore[polars]; extra == 'polars'
Requires-Dist: spinelibs[polars]; extra == 'polars'
Provides-Extra: spark
Requires-Dist: spinecore[spark]; extra == 'spark'
Requires-Dist: spinelibs[spark]; extra == 'spark'
